showstats/__init__.py
showstats/_table.py
showstats/_utils.py
showstats/pl_namespace.py
showstats/showstats.py
showstats-0.0.3.dist-info/METADATA
showstats-0.0.3.dist-info/WHEEL
showstats-0.0.3.dist-info/licenses/LICENSE
showstats-0.0.3.dist-info/RECORD
