Metadata-Version: 2.3
Name: showstats
Version: 0.0.3
Summary: Vertical summary statistics for data frames
Project-URL: Homepage, https://github.com/matthiaskaeding/showstats
Project-URL: Issues, https://github.com/matthiaskaeding/showstats/issues
Project-URL: Changelog, https://github.com/matthiaskaeding/showstats/blob/main/changelog.md
Author: Matthias Kaeding
License-File: LICENSE
Classifier: License :: OSI Approved :: MIT License
Classifier: Operating System :: OS Independent
Classifier: Programming Language :: Python :: 3
Requires-Python: >=3.8
Requires-Dist: polars>=0.20.21
Provides-Extra: pandas
Requires-Dist: pandas>=1.5.3; extra == 'pandas'
Requires-Dist: pyarrow>=10.0.0; extra == 'pandas'
